mindstorm/__init__.py
mindstorm/_modidx.py
mindstorm/core.py
mindstorm_llm-0.0.1.dist-info/LICENSE
mindstorm_llm-0.0.1.dist-info/METADATA
mindstorm_llm-0.0.1.dist-info/WHEEL
mindstorm_llm-0.0.1.dist-info/entry_points.txt
mindstorm_llm-0.0.1.dist-info/top_level.txt
mindstorm_llm-0.0.1.dist-info/RECORD
